tapcode/__init__.py
tapcode/__main__.py
tapcode/tapcode.py
tapcode-1.1.0.dist-info/LICENSE
tapcode-1.1.0.dist-info/METADATA
tapcode-1.1.0.dist-info/WHEEL
tapcode-1.1.0.dist-info/entry_points.txt
tapcode-1.1.0.dist-info/top_level.txt
tapcode-1.1.0.dist-info/RECORD
