Metadata-Version: 2.1
Name: tapcode
Version: 1.1.0
Summary: Prisoner's tap code encryption
Home-page: https://github.com/shadawck/tapcode
Author: shadawck
Author-email: hug211mire@gmail.com
License: MIT
Keywords: crypto cryptography tapcode cipher encryption ctf ctf-tool
Platform: UNKNOWN
Classifier: License :: OSI Approved :: MIT License
Classifier: Programming Language :: Python :: 3
Classifier: Programming Language :: Python :: 3.7
